timecop-timeseries/__init__.py
timecopts/__init__.py
timecopts-1.6.dist-info/LICENSE
timecopts-1.6.dist-info/METADATA
timecopts-1.6.dist-info/WHEEL
timecopts-1.6.dist-info/top_level.txt
timecopts-1.6.dist-info/RECORD
