Metadata-Version: 2.1
Name: timecopts
Version: 1.6
Summary: Simple python library to invoke timecop timeseries
Home-page: https://github.com/BBVA/timecop/
Author: trakuo
Author-email: trakuo@gmail.com
License: UNKNOWN
Platform: UNKNOWN
Classifier: Programming Language :: Python :: 3
Classifier: License :: OSI Approved :: MIT License
Classifier: Operating System :: OS Independent
Requires-Python: >=3.6
Requires-Dist: requests
Requires-Dist: pandas
